NsgOrcFx_nsgeng/NsgOrcFx.py
NsgOrcFx_nsgeng/__init__.py
NsgOrcFx_nsgeng/auxfuncs.py
NsgOrcFx_nsgeng/classes.py
NsgOrcFx_nsgeng/constants.py
NsgOrcFx_nsgeng/environment.py
NsgOrcFx_nsgeng/modal.py
NsgOrcFx_nsgeng/objauxfuncs.py
NsgOrcFx_nsgeng/params.py
NsgOrcFx_nsgeng/sncurves.py
NsgOrcFx_nsgeng/sortlines.py
NsgOrcFx_nsgeng/utils.py
NsgOrcFx_nsgeng/weight.py
NsgOrcFx_nsgeng/weightaux.py
NsgOrcFx_nsgeng-1.0.6.dist-info/LICENSE
NsgOrcFx_nsgeng-1.0.6.dist-info/METADATA
NsgOrcFx_nsgeng-1.0.6.dist-info/WHEEL
NsgOrcFx_nsgeng-1.0.6.dist-info/top_level.txt
NsgOrcFx_nsgeng-1.0.6.dist-info/RECORD
