Metadata-Version: 2.1
Name: NsgOrcFx_nsgeng
Version: 1.0.6
Summary: Package with additional tools to the OrcFxAPI package
Author-email: NSG Engenharia <comercial@nsgeng.com>
Project-URL: Homepage, https://github.com/NSG-Engenharia/NsgOrcFx
Project-URL: Issues, https://github.com/NSG-Engenharia/NsgOrcFx/issues
Classifier: Programming Language :: Python :: 3
Classifier: License :: OSI Approved :: MIT License
Classifier: Operating System :: Microsoft :: Windows
Requires-Python: >=3.8
License-File: LICENSE
